libname/__init__.py
demicestimator-0.0.4.dist-info/METADATA
demicestimator-0.0.4.dist-info/WHEEL
demicestimator-0.0.4.dist-info/top_level.txt
demicestimator-0.0.4.dist-info/RECORD
