Metadata-Version: 2.1
Name: demicestimator
Version: 0.0.4
Summary: A package which can compute the spread of a disease in a population
Home-page: UNKNOWN
Author: Aditya Narendra (ozzey)
Author-email: <adityanarendra6@gmail.com>
License: UNKNOWN
Keywords: python,pandemic,epidemic model,Machine Learning,Prediction,SIR,SEIR
Platform: UNKNOWN
Classifier: Development Status :: 5 - Production/Stable
Classifier: Intended Audience :: Developers
Classifier: Programming Language :: Python :: 3
Classifier: Operating System :: Unix
Classifier: Operating System :: MacOS :: MacOS X
Classifier: Operating System :: Microsoft :: Windows
Classifier: License :: OSI Approved :: MIT License
Requires-Dist: pandas
Requires-Dist: scipy
